{"metadata": {"dbt_schema_version": "https://schemas.getdbt.com/dbt/run-results/v6.json", "dbt_version": "1.8.9", "generated_at": "2025-09-10T23:53:16.098481Z", "invocation_id": "c4d04e9e-2147-45cf-9c7e-91538ab69d61", "env": {}}, "results": [{"status": "success", "timing": [{"name": "compile", "started_at": "2025-09-10T23:53:14.696028Z", "completed_at": "2025-09-10T23:53:14.730744Z"}, {"name": "execute", "started_at": "2025-09-10T23:53:14.731960Z", "completed_at": "2025-09-10T23:53:15.056892Z"}], "thread_id": "Thread-1", "execution_time": 0.3629598617553711, "adapter_response": {"_message": "OK"}, "message": "OK", "failures": null, "unique_id": "model.ex_03_meteo.stg_btc__market_price", "compiled": true, "compiled_code": "-- models/clean/stg_btc__market_price.sql\n\n\nselect\n  cast(id as String)                       as coin_id,\n  cast(symbol as String)                   as symbol,\n  cast(name as String)                     as name,\n  cast(image as String)                    as image_url,\n  toFloat64(current_price)                 as price_usd,\n  toFloat64(market_cap)                    as market_cap_usd,\n  toInt32(market_cap_rank)                 as market_cap_rank,\n  toFloat64(total_volume)                  as total_volume_usd,\n  toFloat64(high_24h)                      as high_24h_usd,\n  toFloat64(low_24h)                       as low_24h_usd,\n  toFloat64(price_change_24h)              as price_change_24h_usd,\n  toFloat64(price_change_percentage_24h)   as price_change_pct_24h,\n\n  -- Normalize last_updated to DateTime64(6,'UTC') whether it's already DT or a String\n  ifNull(\n    parseDateTime64BestEffortOrNull(toString(last_updated), 6, 'UTC'),\n    toDateTime64(last_updated, 6, 'UTC')\n  )                                        as last_updated_utc,\n\n  toTimeZone(\n    ifNull(\n      parseDateTime64BestEffortOrNull(toString(last_updated), 6, 'UTC'),\n      toDateTime64(last_updated, 6, 'UTC')\n    ),\n    'Asia/Manila'\n  )                                        as last_updated_manila\n\nfrom `raw`.`btc___market_price`", "relation_name": "`clean`.`stg_btc__market_price`"}, {"status": "pass", "timing": [{"name": "compile", "started_at": "2025-09-10T23:53:15.094948Z", "completed_at": "2025-09-10T23:53:15.133761Z"}, {"name": "execute", "started_at": "2025-09-10T23:53:15.136538Z", "completed_at": "2025-09-10T23:53:15.408942Z"}], "thread_id": "Thread-4", "execution_time": 0.3394043445587158, "adapter_response": {"_message": "OK"}, "message": null, "failures": 0, "unique_id": "test.ex_03_meteo.not_null_stg_btc__market_price_last_updated_utc.d63cb9517a", "compiled": true, "compiled_code": "\n    \n    \n\n\n\nselect last_updated_utc\nfrom `clean`.`stg_btc__market_price`\nwhere last_updated_utc is null\n\n\n", "relation_name": null}, {"status": "pass", "timing": [{"name": "compile", "started_at": "2025-09-10T23:53:15.074143Z", "completed_at": "2025-09-10T23:53:15.134737Z"}, {"name": "execute", "started_at": "2025-09-10T23:53:15.157017Z", "completed_at": "2025-09-10T23:53:15.415842Z"}], "thread_id": "Thread-3", "execution_time": 0.3473541736602783, "adapter_response": {"_message": "OK"}, "message": null, "failures": 0, "unique_id": "test.ex_03_meteo.not_null_stg_btc__market_price_coin_id.022fc4d0c1", "compiled": true, "compiled_code": "\n    \n    \n\n\n\nselect coin_id\nfrom `clean`.`stg_btc__market_price`\nwhere coin_id is null\n\n\n", "relation_name": null}, {"status": "pass", "timing": [{"name": "compile", "started_at": "2025-09-10T23:53:15.104171Z", "completed_at": "2025-09-10T23:53:15.135671Z"}, {"name": "execute", "started_at": "2025-09-10T23:53:15.172401Z", "completed_at": "2025-09-10T23:53:15.424851Z"}], "thread_id": "Thread-2", "execution_time": 0.3541221618652344, "adapter_response": {"_message": "OK"}, "message": null, "failures": 0, "unique_id": "test.ex_03_meteo.not_null_stg_btc__market_price_price_usd.639627ceb6", "compiled": true, "compiled_code": "\n    \n    \n\n\n\nselect price_usd\nfrom `clean`.`stg_btc__market_price`\nwhere price_usd is null\n\n\n", "relation_name": null}, {"status": "success", "timing": [{"name": "compile", "started_at": "2025-09-10T23:53:15.467609Z", "completed_at": "2025-09-10T23:53:15.522460Z"}, {"name": "execute", "started_at": "2025-09-10T23:53:15.586523Z", "completed_at": "2025-09-10T23:53:15.943381Z"}], "thread_id": "Thread-3", "execution_time": 0.5081324577331543, "adapter_response": {"_message": "OK"}, "message": "OK", "failures": null, "unique_id": "model.ex_03_meteo.vw_btc__latest_24h", "compiled": true, "compiled_code": "\n\nWITH (SELECT max(last_updated_utc) FROM `clean`.`stg_btc__market_price`) AS ts_max\nSELECT\n  *\nFROM `clean`.`stg_btc__market_price`\nWHERE last_updated_utc >= ts_max - INTERVAL 24 HOUR\nORDER BY last_updated_utc", "relation_name": "`mart`.`vw_btc__latest_24h`"}, {"status": "success", "timing": [{"name": "compile", "started_at": "2025-09-10T23:53:15.458776Z", "completed_at": "2025-09-10T23:53:15.521705Z"}, {"name": "execute", "started_at": "2025-09-10T23:53:15.543723Z", "completed_at": "2025-09-10T23:53:16.053260Z"}], "thread_id": "Thread-4", "execution_time": 0.6186845302581787, "adapter_response": {"_message": "OK"}, "message": "OK", "failures": null, "unique_id": "model.ex_03_meteo.mart_btc__market_price_hourly", "compiled": true, "compiled_code": "\n\nwith base as (\n  select\n    -- non-nullable for MergeTree keys\n    toStartOfHour(toTimeZone(assumeNotNull(last_updated_utc), 'Asia/Manila')) as hour_local,\n    assumeNotNull(coin_id)                                                    as coin_id,\n    last_updated_utc,\n    toFloat64(price_usd)                                                      as price_usd\n  from `clean`.`stg_btc__market_price`\n  where last_updated_utc is not null\n\n  \n    -- Recompute only latest (and previous) Manila hours\n    and toStartOfHour(toTimeZone(last_updated_utc,'Asia/Manila')) >= (\n      select coalesce(max(hour_local), toStartOfHour(now('Asia/Manila')) - interval 1 hour)\n      from `mart`.`mart_btc__market_price_hourly`\n    ) - interval 1 hour\n  \n)\nselect\n  hour_local,\n  coin_id,\n  min(price_usd)                      as low_usd,\n  max(price_usd)                      as high_usd,\n  argMin(price_usd, last_updated_utc) as open_usd,   -- first in hour\n  argMax(price_usd, last_updated_utc) as close_usd   -- last in hour\nfrom base\ngroup by hour_local, coin_id\norder by hour_local, coin_id", "relation_name": "`mart`.`mart_btc__market_price_hourly`"}, {"status": "success", "timing": [{"name": "compile", "started_at": "2025-09-10T23:53:15.438612Z", "completed_at": "2025-09-10T23:53:15.520572Z"}, {"name": "execute", "started_at": "2025-09-10T23:53:15.523251Z", "completed_at": "2025-09-10T23:53:16.080756Z"}], "thread_id": "Thread-1", "execution_time": 0.6471166610717773, "adapter_response": {"_message": "OK"}, "message": "OK", "failures": null, "unique_id": "model.ex_03_meteo.mart_btc__daily_ohlc", "compiled": true, "compiled_code": "\n\nwith base as (\n  select\n    assumeNotNull(toDate(toTimeZone(last_updated_utc,'Asia/Manila'))) as day_local,\n    assumeNotNull(coin_id)                                            as coin_id,\n    last_updated_utc,\n    toFloat64(price_usd)                                              as price_usd\n  from `clean`.`stg_btc__market_price`\n  where last_updated_utc is not null\n\n  \n    -- Recompute only latest (and previous) Manila days\n    and toDate(toTimeZone(last_updated_utc,'Asia/Manila')) >= (\n      select coalesce(max(day_local), toDate(now('Asia/Manila')) - 1)\n      from `mart`.`mart_btc__daily_ohlc`\n    ) - 1\n  \n)\nselect\n  day_local,\n  coin_id,\n  min(price_usd)                      as low_usd,\n  max(price_usd)                      as high_usd,\n  argMin(price_usd, last_updated_utc) as open_usd,   -- first in day\n  argMax(price_usd, last_updated_utc) as close_usd   -- last in day\nfrom base\ngroup by day_local, coin_id\norder by day_local, coin_id", "relation_name": "`mart`.`mart_btc__daily_ohlc`"}], "elapsed_time": 1.8143117427825928, "args": {"show_resource_report": false, "log_file_max_bytes": 10485760, "exclude": [], "cache_selected_only": false, "printer_width": 80, "quiet": false, "indirect_selection": "eager", "log_level": "info", "which": "build", "write_json": true, "static_parser": true, "source_freshness_run_project_hooks": false, "profiles_dir": ".", "send_anonymous_usage_stats": true, "enable_legacy_logger": false, "vars": {}, "favor_state": false, "log_format": "default", "populate_cache": true, "use_colors": true, "defer": false, "project_dir": "/workdir/transforms/04_btc", "log_path": "/workdir/transforms/04_btc/logs", "introspect": true, "target": "local", "require_explicit_package_overrides_for_builtin_materializations": true, "invocation_command": "dbt build --profiles-dir . --target local", "show": false, "print": true, "partial_parse_file_diff": true, "version_check": true, "require_resource_names_without_spaces": false, "select": [], "strict_mode": false, "partial_parse": true, "exclude_resource_types": [], "include_saved_query": false, "warn_error_options": {"include": [], "exclude": []}, "export_saved_queries": false, "empty": false, "log_format_file": "debug", "log_level_file": "debug", "use_colors_file": true, "macro_debugging": false, "resource_types": []}}