{"metadata": {"dbt_schema_version": "https://schemas.getdbt.com/dbt/run-results/v6.json", "dbt_version": "1.8.9", "generated_at": "2025-09-11T09:27:11.912438Z", "invocation_id": "fbde23a1-baa9-454a-b5be-233683ba01b6", "env": {}}, "results": [{"status": "success", "timing": [{"name": "compile", "started_at": "2025-09-11T09:27:03.368776Z", "completed_at": "2025-09-11T09:27:03.386195Z"}, {"name": "execute", "started_at": "2025-09-11T09:27:03.387044Z", "completed_at": "2025-09-11T09:27:07.577415Z"}], "thread_id": "Thread-1", "execution_time": 4.210611581802368, "adapter_response": {"_message": "OK"}, "message": "OK", "failures": null, "unique_id": "model.ex_01_mpg.mpg_standardized", "compiled": true, "compiled_code": "\n\n-- Source columns are already Nullable with correct types.\n-- Keep them as-is to preserve nullability and avoid insert errors.\n\nselect\n  mpg,            -- Nullable(Float64)\n  cylinders,      -- Nullable(Int64)\n  displacement,   -- Nullable(Float64)\n  horsepower,     -- Nullable(Float64)\n  /*\n  coalesce(\n        horsepower,\n        avg(horsepower) over (partition by cylinders)\n    ) as horsepower_imputed,\n  */\n  weight,         -- Nullable(Int64)\n  acceleration,   -- Nullable(Float64)\n  model_year,     -- Nullable(Int64)\n  origin,         -- Nullable(String)\n  name as make    -- Nullable(String)\nfrom `raw`.`autompg___cars`", "relation_name": "`clean`.`mpg_standardized`"}, {"status": "success", "timing": [{"name": "compile", "started_at": "2025-09-11T09:27:07.586929Z", "completed_at": "2025-09-11T09:27:07.593574Z"}, {"name": "execute", "started_at": "2025-09-11T09:27:07.594367Z", "completed_at": "2025-09-11T09:27:11.883472Z"}], "thread_id": "Thread-3", "execution_time": 4.29859471321106, "adapter_response": {"_message": "OK"}, "message": "OK", "failures": null, "unique_id": "model.ex_01_mpg.cylinders_by_origin", "compiled": true, "compiled_code": "\n\nselect\n  origin,\n  avg(cylinders) as avg_cylinders,\n  count()        as n\nfrom `clean`.`mpg_standardized`\ngroup by origin", "relation_name": "`mart`.`cylinders_by_origin`"}], "elapsed_time": 12.558169603347778, "args": {"export_saved_queries": false, "log_format": "default", "source_freshness_run_project_hooks": false, "select": [], "indirect_selection": "eager", "profiles_dir": ".", "send_anonymous_usage_stats": true, "project_dir": "/workdir/transforms/01_mpg", "printer_width": 80, "log_level_file": "debug", "log_format_file": "debug", "log_level": "info", "partial_parse_file_diff": true, "defer": false, "require_resource_names_without_spaces": false, "introspect": true, "vars": {}, "write_json": true, "exclude": [], "cache_selected_only": false, "print": true, "empty": false, "quiet": false, "warn_error_options": {"include": [], "exclude": []}, "version_check": true, "static_parser": true, "log_path": "/workdir/transforms/01_mpg/logs", "show_resource_report": false, "macro_debugging": false, "populate_cache": true, "target": "remote", "use_colors_file": true, "which": "build", "enable_legacy_logger": false, "use_colors": true, "partial_parse": true, "resource_types": [], "show": false, "strict_mode": false, "favor_state": false, "include_saved_query": false, "exclude_resource_types": [], "invocation_command": "dbt build --profiles-dir . --target remote", "log_file_max_bytes": 10485760, "require_explicit_package_overrides_for_builtin_materializations": true}}